hypatorch/__init__.py
hypatorch/assessments.py
hypatorch/core.py
hypatorch/losses.py
hypatorch/utils.py
hypatorch-0.2.14.dist-info/LICENSE
hypatorch-0.2.14.dist-info/METADATA
hypatorch-0.2.14.dist-info/WHEEL
hypatorch-0.2.14.dist-info/top_level.txt
hypatorch-0.2.14.dist-info/RECORD
