Metadata-Version: 2.1
Name: hypatorch
Version: 0.2.14
Summary: HypaTorch: A library for abstract and visual model configuration
Home-page: https://github.com/Altavo/hypatorch/
Author: Altavo GmbH
License: Apache 2.0
License-File: LICENSE
Requires-Dist: torch
Requires-Dist: hydra-core
Requires-Dist: lightning
Requires-Dist: omegaconf
